LICENSE
MANIFEST.in
README.md
setup.py
cbpi4_GroupedSensor/__init__.py
cbpi4_GroupedSensor/config.yaml
cbpi4_GroupedSensor.egg-info/PKG-INFO
cbpi4_GroupedSensor.egg-info/SOURCES.txt
cbpi4_GroupedSensor.egg-info/dependency_links.txt
cbpi4_GroupedSensor.egg-info/top_level.txt