Metadata-Version: 2.1
Name: cbpi4-GroupedSensor
Version: 0.0.4
Summary: CraftBeerPi4 Sensor Plugin
Home-page: https://github.com/avollkopf/cbpi4_GroupedSensor
Author: A. Vollkopf, B. Helm
Author-email: avollkopf@web.de
License: UNKNOWN
Platform: UNKNOWN
License-File: LICENSE
